arches_component_lab/__init__.py
arches_component_lab/apps.py
arches_component_lab/arches_component_lab_urls.py
arches_component_lab/celery.py
arches_component_lab/hosts.py
arches_component_lab/models.py
arches_component_lab/settings.py
arches_component_lab/urls.py
arches_component_lab/wsgi.py
arches_component_lab/datatypes/__init__.py
arches_component_lab/functions/__init__.py
arches_component_lab/locale/.gitkeep
arches_component_lab/management/__init__.py
arches_component_lab/management/commands/__init__.py
arches_component_lab/media/css/themes/_project.scss
arches_component_lab/media/img/favicon.png
arches_component_lab/media/js/.gitkeep
arches_component_lab/migrations/0001_initial.py
arches_component_lab/migrations/0002_populate_widget_mappings.py
arches_component_lab/migrations/__init__.py
arches_component_lab/search_components/__init__.py
arches_component_lab/search_indexes/__init__.py
arches_component_lab/src/arches_component_lab/declarations.d.ts
arches_component_lab/src/arches_component_lab/types.ts
arches_component_lab/src/arches_component_lab/utils.ts
arches_component_lab/src/arches_component_lab/datatypes/boolean/types.ts
arches_component_lab/src/arches_component_lab/datatypes/concept/api.ts
arches_component_lab/src/arches_component_lab/datatypes/concept/types.ts
arches_component_lab/src/arches_component_lab/datatypes/concept/utils.ts
arches_component_lab/src/arches_component_lab/datatypes/concept-list/api.ts
arches_component_lab/src/arches_component_lab/datatypes/concept-list/types.ts
arches_component_lab/src/arches_component_lab/datatypes/concept-list/utils.ts
arches_component_lab/src/arches_component_lab/datatypes/date/types.ts
arches_component_lab/src/arches_component_lab/datatypes/date/utils.ts
arches_component_lab/src/arches_component_lab/datatypes/domain/types.ts
arches_component_lab/src/arches_component_lab/datatypes/edtf/types.ts
arches_component_lab/src/arches_component_lab/datatypes/file-list/constants.ts
arches_component_lab-0.0.1a6.dist-info/licenses/LICENSE
arches_component_lab-0.0.1a6.dist-info/METADATA
arches_component_lab-0.0.1a6.dist-info/WHEEL
arches_component_lab-0.0.1a6.dist-info/top_level.txt
arches_component_lab-0.0.1a6.dist-info/RECORD
