Metadata-Version: 2.4
Name: arches-component-lab
Version: 0.0.1a6
Author: Arches Project
License-Expression: AGPL-3.0-or-later
Project-URL: Homepage, https://archesproject.org/
Project-URL: Documentation, https://arches.readthedocs.io
Project-URL: Repository, https://github.com/archesproject/arches-component-lab.git
Project-URL: Issues, https://github.com/archesproject/arches-component-lab/issues
Classifier: Development Status :: 3 - Alpha
Classifier: Framework :: Django
Classifier: Framework :: Django :: 4.2
Classifier: Framework :: Django :: 5.2
Classifier: Intended Audience :: Developers
Classifier: Intended Audience :: Information Technology
Classifier: Intended Audience :: Science/Research
Classifier: Programming Language :: Python
Classifier: Programming Language :: Python :: 3
Classifier: Programming Language :: Python :: 3 :: Only
Classifier: Programming Language :: Python :: 3.10
Classifier: Programming Language :: Python :: 3.11
Classifier: Programming Language :: Python :: 3.12
Classifier: Programming Language :: Python :: 3.13
Requires-Python: >=3.10
License-File: LICENSE
Requires-Dist: arches>=7.6.9
Requires-Dist: arches-querysets[drf]>=1.0.0
Provides-Extra: dev
Requires-Dist: black==24.4.2; extra == "dev"
Requires-Dist: coverage; extra == "dev"
Requires-Dist: django-silk==5.1.0; extra == "dev"
Requires-Dist: livereload; extra == "dev"
Requires-Dist: pre-commit==3.8.0; extra == "dev"
Requires-Dist: sst; extra == "dev"
Dynamic: license-file
